Terminus/__init__.py
Terminus/__main__.py
Terminus/celery.py
Terminus/commons.py
Terminus/job_status.py
Terminus/tasks.py
Terminus/etc/bash_service_template.json
Terminus/etc/job.py
Terminus/etc/python_service_template.json
Terminus/etc/service_template.py
Terminus/etc/terminus.env
Terminus/etc/terminus.service
Terminus/jobs/__init__.py
Terminus/jobs/tjob.py
Terminus/jobs/slurm_submit/__init__.py
Terminus/jobs/slurm_submit/job_submitter.py
Terminus/services_example/datacube_3d_hydro/datacube_3d_hydro.py
Terminus/services_example/datacube_3d_hydro/service.json
Terminus/services_example/datacube_3d_mhd/datacube_3d_mhd.py
Terminus/services_example/datacube_3d_mhd/service.json
Terminus/services_example/rt_density_map/rt_density_map.py
Terminus/services_example/rt_density_map/service.json
galactica_terminus-0.7.dist-info/LICENSE
galactica_terminus-0.7.dist-info/METADATA
galactica_terminus-0.7.dist-info/WHEEL
galactica_terminus-0.7.dist-info/entry_points.txt
galactica_terminus-0.7.dist-info/top_level.txt
galactica_terminus-0.7.dist-info/RECORD
